[
  {
    "business_name": "Ramos Tax & Services",
    "business_category": "accountant",
    "city": "elgin",
    "address": "308 Dundee Ave, Elgin, IL 60120, USA",
    "phone_number": "(224) 629-4030",
    "website_url": "http://www.ramostax.com/",
    "google_maps_url": "https://maps.google.com/?cid=9422114515158239117&g_mp=Cidnb29nbGUubWFwcy5wbGFjZXMudjEuUGxhY2VzLlNlYXJjaFRleHQQAhgEIAA",
    "rating": 4.6,
    "review_count": 106,
    "pixel_audit": {
      "tracking_score": 0,
      "any_retargeting": false,
      "facebook_pixel": false,
      "facebook_pixel_id": "",
      "google_ads_remarketing": false,
      "google_ads_id": "",
      "google_analytics": false,
      "google_tag_manager": false,
      "tiktok_pixel": false,
      "linkedin_insight": false,
      "hotjar": false,
      "any_tag_manager": false,
      "missing": [
        "all \u2014 page not fetched"
      ],
      "found": [],
      "google_ads_conversion": false,
      "pages_scanned": [
        "http://www.ramostax.com/",
        "http://www.ramostax.com/contact",
        "http://www.ramostax.com/contact/",
        "http://www.ramostax.com/services/"
      ],
      "source": "playwright_v2"
    },
    "fetch_status": "http_403",
    "_source": "google_maps_pixel_audit",
    "opportunity_score": 487.6,
    "pixels_v2": {
      "status": "ok",
      "error": null,
      "facebook_pixel": false,
      "google_ads_remarketing": false,
      "google_ads_conversion": false,
      "google_analytics": false,
      "google_tag_manager": false,
      "linkedin_insight": false,
      "tiktok_pixel": false,
      "any_retargeting": false,
      "pages_scanned": [
        "http://www.ramostax.com/",
        "http://www.ramostax.com/contact",
        "http://www.ramostax.com/contact/",
        "http://www.ramostax.com/services/"
      ],
      "errors": [],
      "source": "playwright_v2"
    },
    "pixel_audit_status": "ok"
  },
  {
    "business_name": "AE Accounting Group",
    "business_category": "accountant",
    "city": "elgin",
    "address": "1000 W Spring St Unit 2D, South Elgin, IL 60177, USA",
    "phone_number": "(847) 857-7721",
    "website_url": "http://www.aeaccountingco.com/",
    "google_maps_url": "https://maps.google.com/?cid=13897274204806611288&g_mp=Cidnb29nbGUubWFwcy5wbGFjZXMudjEuUGxhY2VzLlNlYXJjaFRleHQQAhgEIAA",
    "rating": 4.9,
    "review_count": 47,
    "pixel_audit": {
      "tracking_score": 0,
      "any_retargeting": false,
      "facebook_pixel": false,
      "facebook_pixel_id": "",
      "google_ads_remarketing": false,
      "google_ads_id": "",
      "google_analytics": false,
      "google_tag_manager": false,
      "tiktok_pixel": false,
      "linkedin_insight": false,
      "hotjar": false,
      "any_tag_manager": false,
      "missing": [
        "facebook_pixel",
        "google_ads_remarketing",
        "google_analytics",
        "google_tag_manager",
        "tiktok_pixel",
        "linkedin_insight"
      ],
      "found": [],
      "google_ads_conversion": false,
      "pages_scanned": [
        "http://www.aeaccountingco.com/"
      ],
      "source": "playwright_v2"
    },
    "fetch_status": "ok",
    "_source": "google_maps_pixel_audit",
    "opportunity_score": 230.3,
    "pixels_v2": {
      "status": "ok",
      "error": null,
      "facebook_pixel": false,
      "google_ads_remarketing": false,
      "google_ads_conversion": false,
      "google_analytics": false,
      "google_tag_manager": false,
      "linkedin_insight": false,
      "tiktok_pixel": false,
      "any_retargeting": false,
      "pages_scanned": [
        "http://www.aeaccountingco.com/"
      ],
      "errors": [],
      "source": "playwright_v2"
    },
    "pixel_audit_status": "ok"
  },
  {
    "business_name": "BeanLab Accounting and Advisory",
    "business_category": "accountant",
    "city": "elgin",
    "address": "1275 Davis Rd #120, Elgin, IL 60123, USA",
    "phone_number": "(847) 264-4662",
    "website_url": "http://beanlab.com/",
    "google_maps_url": "https://maps.google.com/?cid=6111329863477408127&g_mp=Cidnb29nbGUubWFwcy5wbGFjZXMudjEuUGxhY2VzLlNlYXJjaFRleHQQAhgEIAA",
    "rating": 5,
    "review_count": 54,
    "pixel_audit": {
      "tracking_score": 15,
      "any_retargeting": false,
      "facebook_pixel": false,
      "facebook_pixel_id": "",
      "google_ads_remarketing": false,
      "google_ads_id": "",
      "google_analytics": true,
      "google_tag_manager": false,
      "tiktok_pixel": false,
      "linkedin_insight": false,
      "hotjar": false,
      "any_tag_manager": false,
      "missing": [
        "facebook_pixel",
        "google_ads_remarketing",
        "google_tag_manager",
        "tiktok_pixel",
        "linkedin_insight"
      ],
      "found": [
        "google_analytics"
      ],
      "google_ads_conversion": false,
      "pages_scanned": [
        "http://beanlab.com/",
        "http://beanlab.com/contact/"
      ],
      "source": "playwright_v2"
    },
    "fetch_status": "ok",
    "_source": "google_maps_pixel_audit",
    "opportunity_score": 229.5,
    "pixels_v2": {
      "status": "ok",
      "error": null,
      "facebook_pixel": false,
      "google_ads_remarketing": false,
      "google_ads_conversion": false,
      "google_analytics": true,
      "google_tag_manager": false,
      "linkedin_insight": false,
      "tiktok_pixel": false,
      "any_retargeting": false,
      "pages_scanned": [
        "http://beanlab.com/",
        "http://beanlab.com/contact/"
      ],
      "errors": [],
      "source": "playwright_v2"
    },
    "pixel_audit_status": "ok"
  },
  {
    "business_name": "Hopp Accounting & Tax Services",
    "business_category": "accountant",
    "city": "elgin",
    "address": "804 Walnut Ave, Elgin, IL 60123, USA",
    "phone_number": "(847) 742-8386",
    "website_url": "http://www.hoppcpa.com/",
    "google_maps_url": "https://maps.google.com/?cid=15677690848719249446&g_mp=Cidnb29nbGUubWFwcy5wbGFjZXMudjEuUGxhY2VzLlNlYXJjaFRleHQQAhgEIAA",
    "rating": 4.8,
    "review_count": 45,
    "pixel_audit": {
      "tracking_score": 15,
      "any_retargeting": false,
      "facebook_pixel": false,
      "facebook_pixel_id": "",
      "google_ads_remarketing": false,
      "google_ads_id": "",
      "google_analytics": true,
      "google_tag_manager": false,
      "tiktok_pixel": false,
      "linkedin_insight": false,
      "hotjar": false,
      "any_tag_manager": false,
      "missing": [
        "facebook_pixel",
        "google_ads_remarketing",
        "google_tag_manager",
        "tiktok_pixel",
        "linkedin_insight"
      ],
      "found": [
        "google_analytics"
      ],
      "google_ads_conversion": false,
      "pages_scanned": [
        "http://www.hoppcpa.com/",
        "http://www.hoppcpa.com/contact"
      ],
      "source": "playwright_v2"
    },
    "fetch_status": "ok",
    "_source": "google_maps_pixel_audit",
    "opportunity_score": 183.6,
    "pixels_v2": {
      "status": "ok",
      "error": null,
      "facebook_pixel": false,
      "google_ads_remarketing": false,
      "google_ads_conversion": false,
      "google_analytics": true,
      "google_tag_manager": false,
      "linkedin_insight": false,
      "tiktok_pixel": false,
      "any_retargeting": false,
      "pages_scanned": [
        "http://www.hoppcpa.com/",
        "http://www.hoppcpa.com/contact"
      ],
      "errors": [],
      "source": "playwright_v2"
    },
    "pixel_audit_status": "ok"
  },
  {
    "business_name": "M.E.M. Accounting & Tax Services Inc.",
    "business_category": "accountant",
    "city": "elgin",
    "address": "1425 N McLean Blvd Suite 400, Elgin, IL 60123, USA",
    "phone_number": "(847) 841-1887",
    "website_url": "https://memaccounting.com/",
    "google_maps_url": "https://maps.google.com/?cid=4128844647863895234&g_mp=Cidnb29nbGUubWFwcy5wbGFjZXMudjEuUGxhY2VzLlNlYXJjaFRleHQQAhgEIAA",
    "rating": 5,
    "review_count": 16,
    "pixel_audit": {
      "tracking_score": 0,
      "any_retargeting": false,
      "facebook_pixel": false,
      "facebook_pixel_id": "",
      "google_ads_remarketing": false,
      "google_ads_id": "",
      "google_analytics": false,
      "google_tag_manager": false,
      "tiktok_pixel": false,
      "linkedin_insight": false,
      "hotjar": false,
      "any_tag_manager": false,
      "missing": [
        "all \u2014 page not fetched"
      ],
      "found": [],
      "google_ads_conversion": false,
      "pages_scanned": [
        "https://memaccounting.com/"
      ],
      "source": "playwright_v2"
    },
    "fetch_status": "network_error",
    "_source": "google_maps_pixel_audit",
    "opportunity_score": 80.0,
    "pixels_v2": {
      "status": "ok",
      "error": null,
      "facebook_pixel": false,
      "google_ads_remarketing": false,
      "google_ads_conversion": false,
      "google_analytics": false,
      "google_tag_manager": false,
      "linkedin_insight": false,
      "tiktok_pixel": false,
      "any_retargeting": false,
      "pages_scanned": [
        "https://memaccounting.com/"
      ],
      "errors": [],
      "source": "playwright_v2"
    },
    "pixel_audit_status": "ok"
  },
  {
    "business_name": "Northgate Accounting Services",
    "business_category": "accountant",
    "city": "elgin",
    "address": "Level 1, 26 Thunderton Pl, Elgin IV30 1JB, UK",
    "phone_number": "0141 471 5729",
    "website_url": "https://northgateaccounting.co.uk/",
    "google_maps_url": "https://maps.google.com/?cid=2833792718597756170&g_mp=Cidnb29nbGUubWFwcy5wbGFjZXMudjEuUGxhY2VzLlNlYXJjaFRleHQQAhgEIAA",
    "rating": 5,
    "review_count": 13,
    "pixel_audit": {
      "tracking_score": 0,
      "any_retargeting": false,
      "facebook_pixel": false,
      "facebook_pixel_id": "",
      "google_ads_remarketing": false,
      "google_ads_id": "",
      "google_analytics": false,
      "google_tag_manager": false,
      "tiktok_pixel": false,
      "linkedin_insight": false,
      "hotjar": false,
      "any_tag_manager": false,
      "missing": [
        "facebook_pixel",
        "google_ads_remarketing",
        "google_analytics",
        "google_tag_manager",
        "tiktok_pixel",
        "linkedin_insight"
      ],
      "found": [],
      "google_ads_conversion": false,
      "pages_scanned": [
        "https://northgateaccounting.co.uk/",
        "https://northgateaccounting.co.uk/get-a-quote"
      ],
      "source": "playwright_v2"
    },
    "fetch_status": "ok",
    "_source": "google_maps_pixel_audit",
    "opportunity_score": 65.0,
    "pixels_v2": {
      "status": "ok",
      "error": null,
      "facebook_pixel": false,
      "google_ads_remarketing": false,
      "google_ads_conversion": false,
      "google_analytics": false,
      "google_tag_manager": false,
      "linkedin_insight": false,
      "tiktok_pixel": false,
      "any_retargeting": false,
      "pages_scanned": [
        "https://northgateaccounting.co.uk/",
        "https://northgateaccounting.co.uk/get-a-quote"
      ],
      "errors": [],
      "source": "playwright_v2"
    },
    "pixel_audit_status": "ok"
  },
  {
    "business_name": "B & R Tax and Accounting",
    "business_category": "accountant",
    "city": "elgin",
    "address": "1315 N La Fox St, South Elgin, IL 60177, USA",
    "phone_number": "(847) 888-4494",
    "website_url": "http://www.bandrtax.com/",
    "google_maps_url": "https://maps.google.com/?cid=17693030388004110839&g_mp=Cidnb29nbGUubWFwcy5wbGFjZXMudjEuUGxhY2VzLlNlYXJjaFRleHQQAhgEIAA",
    "rating": 5,
    "review_count": 12,
    "pixel_audit": {
      "tracking_score": 0,
      "any_retargeting": false,
      "facebook_pixel": false,
      "facebook_pixel_id": "",
      "google_ads_remarketing": false,
      "google_ads_id": "",
      "google_analytics": false,
      "google_tag_manager": false,
      "tiktok_pixel": false,
      "linkedin_insight": false,
      "hotjar": false,
      "any_tag_manager": false,
      "missing": [
        "facebook_pixel",
        "google_ads_remarketing",
        "google_analytics",
        "google_tag_manager",
        "tiktok_pixel",
        "linkedin_insight"
      ],
      "found": [],
      "google_ads_conversion": false,
      "pages_scanned": [
        "http://www.bandrtax.com/"
      ],
      "source": "playwright_v2"
    },
    "fetch_status": "ok",
    "_source": "google_maps_pixel_audit",
    "opportunity_score": 60.0,
    "pixels_v2": {
      "status": "ok",
      "error": null,
      "facebook_pixel": false,
      "google_ads_remarketing": false,
      "google_ads_conversion": false,
      "google_analytics": false,
      "google_tag_manager": false,
      "linkedin_insight": false,
      "tiktok_pixel": false,
      "any_retargeting": false,
      "pages_scanned": [
        "http://www.bandrtax.com/"
      ],
      "errors": [],
      "source": "playwright_v2"
    },
    "pixel_audit_status": "ok"
  },
  {
    "business_name": "Ward Lane & Associates",
    "business_category": "accountant",
    "city": "elgin",
    "address": "1250 Larkin Ave #200, Elgin, IL 60123, USA",
    "phone_number": "(847) 742-7294",
    "website_url": "https://www.wardlane.com/",
    "google_maps_url": "https://maps.google.com/?cid=6229547882986954018&g_mp=Cidnb29nbGUubWFwcy5wbGFjZXMudjEuUGxhY2VzLlNlYXJjaFRleHQQAhgEIAA",
    "rating": 4.5,
    "review_count": 8,
    "pixel_audit": {
      "tracking_score": 0,
      "any_retargeting": false,
      "facebook_pixel": false,
      "facebook_pixel_id": "",
      "google_ads_remarketing": false,
      "google_ads_id": "",
      "google_analytics": false,
      "google_tag_manager": false,
      "tiktok_pixel": false,
      "linkedin_insight": false,
      "hotjar": false,
      "any_tag_manager": false,
      "missing": [
        "facebook_pixel",
        "google_ads_remarketing",
        "google_analytics",
        "google_tag_manager",
        "tiktok_pixel",
        "linkedin_insight"
      ],
      "found": [],
      "google_ads_conversion": false,
      "pages_scanned": [
        "https://www.wardlane.com/",
        "https://www.wardlane.com/contact-us",
        "https://www.wardlane.com/services"
      ],
      "source": "playwright_v2"
    },
    "fetch_status": "ok",
    "_source": "google_maps_pixel_audit",
    "opportunity_score": 36.0,
    "pixels_v2": {
      "status": "ok",
      "error": null,
      "facebook_pixel": false,
      "google_ads_remarketing": false,
      "google_ads_conversion": false,
      "google_analytics": false,
      "google_tag_manager": false,
      "linkedin_insight": false,
      "tiktok_pixel": false,
      "any_retargeting": false,
      "pages_scanned": [
        "https://www.wardlane.com/",
        "https://www.wardlane.com/contact-us",
        "https://www.wardlane.com/services"
      ],
      "errors": [],
      "source": "playwright_v2"
    },
    "pixel_audit_status": "ok"
  },
  {
    "business_name": "Cathedral Accountancy Ltd",
    "business_category": "accountant",
    "city": "elgin",
    "address": "4 N Guildry St, Elgin IV30 1JR, UK",
    "phone_number": "01343 551572",
    "website_url": "http://www.thelongpartnership.co.uk/",
    "google_maps_url": "https://maps.google.com/?cid=3843323470316583734&g_mp=Cidnb29nbGUubWFwcy5wbGFjZXMudjEuUGxhY2VzLlNlYXJjaFRleHQQAhgEIAA",
    "rating": 5,
    "review_count": 2,
    "pixel_audit": {
      "tracking_score": 0,
      "any_retargeting": false,
      "facebook_pixel": false,
      "facebook_pixel_id": "",
      "google_ads_remarketing": false,
      "google_ads_id": "",
      "google_analytics": false,
      "google_tag_manager": false,
      "tiktok_pixel": false,
      "linkedin_insight": false,
      "hotjar": false,
      "any_tag_manager": false,
      "missing": [
        "all \u2014 page not fetched"
      ],
      "found": [],
      "audit_gap": "Error: Page.goto: net::ERR_ADDRESS_UNREACHABLE at http://www.thelongpartnership.co.uk/\nCall log:\n  - navigating to \"http://www.thelongpartnership.co.uk/\", waiting unti"
    },
    "fetch_status": "network_error",
    "_source": "google_maps_pixel_audit",
    "opportunity_score": 10.0,
    "pixels_v2": {
      "status": "error",
      "error": "Error: Page.goto: net::ERR_ADDRESS_UNREACHABLE at http://www.thelongpartnership.co.uk/\nCall log:\n  - navigating to \"http://www.thelongpartnership.co.uk/\", waiting unti",
      "facebook_pixel": false,
      "google_ads_remarketing": false,
      "google_ads_conversion": false,
      "google_analytics": false,
      "google_tag_manager": false,
      "linkedin_insight": false,
      "tiktok_pixel": false,
      "any_retargeting": false,
      "pages_scanned": [],
      "errors": [
        "home: Error: Page.goto: net::ERR_ADDRESS_UNREACHABLE at http://www.thelongpartnership.co.uk/\nCall log:\n  - navigating to \"http://www.thelongpartnership.co.uk/\", waiting unti"
      ],
      "source": "playwright_v2"
    },
    "pixel_audit_status": "error"
  },
  {
    "business_name": "Hopes & Co. Accounting",
    "business_category": "accountant",
    "city": "elgin",
    "address": "14 Chanonry Rd S, Elgin IV30 6NG, UK",
    "phone_number": "01343 357112",
    "website_url": "https://www.hopesaccounting.co.uk/",
    "google_maps_url": "https://maps.google.com/?cid=4638555624108205466&g_mp=Cidnb29nbGUubWFwcy5wbGFjZXMudjEuUGxhY2VzLlNlYXJjaFRleHQQAhgEIAA",
    "rating": 5,
    "review_count": 2,
    "pixel_audit": {
      "tracking_score": 0,
      "any_retargeting": false,
      "facebook_pixel": false,
      "facebook_pixel_id": "",
      "google_ads_remarketing": false,
      "google_ads_id": "",
      "google_analytics": true,
      "google_tag_manager": false,
      "tiktok_pixel": false,
      "linkedin_insight": false,
      "hotjar": false,
      "any_tag_manager": false,
      "missing": [
        "facebook_pixel",
        "google_ads_remarketing",
        "google_analytics",
        "google_tag_manager",
        "tiktok_pixel",
        "linkedin_insight"
      ],
      "found": [],
      "google_ads_conversion": false,
      "pages_scanned": [
        "https://www.hopesaccounting.co.uk/",
        "https://www.hopesaccounting.co.uk/contact-us",
        "https://www.hopesaccounting.co.uk/services"
      ],
      "source": "playwright_v2"
    },
    "fetch_status": "ok",
    "_source": "google_maps_pixel_audit",
    "opportunity_score": 10.0,
    "pixels_v2": {
      "status": "ok",
      "error": null,
      "facebook_pixel": false,
      "google_ads_remarketing": false,
      "google_ads_conversion": false,
      "google_analytics": true,
      "google_tag_manager": false,
      "linkedin_insight": false,
      "tiktok_pixel": false,
      "any_retargeting": false,
      "pages_scanned": [
        "https://www.hopesaccounting.co.uk/",
        "https://www.hopesaccounting.co.uk/contact-us",
        "https://www.hopesaccounting.co.uk/services"
      ],
      "errors": [],
      "source": "playwright_v2"
    },
    "pixel_audit_status": "ok"
  },
  {
    "business_name": "Porte Brown LLC - Elgin",
    "business_category": "accountant",
    "city": "elgin",
    "address": "1752 Capital St #400, Elgin, IL 60124, USA",
    "phone_number": "(847) 695-1775",
    "website_url": "https://www.portebrown.com/office-locations/elgin",
    "google_maps_url": "https://maps.google.com/?cid=10975612849695391050&g_mp=Cidnb29nbGUubWFwcy5wbGFjZXMudjEuUGxhY2VzLlNlYXJjaFRleHQQAhgEIAA",
    "rating": 5,
    "review_count": 2,
    "pixel_audit": {
      "tracking_score": 15,
      "any_retargeting": false,
      "facebook_pixel": false,
      "facebook_pixel_id": "",
      "google_ads_remarketing": false,
      "google_ads_id": "",
      "google_analytics": true,
      "google_tag_manager": false,
      "tiktok_pixel": false,
      "linkedin_insight": false,
      "hotjar": false,
      "any_tag_manager": false,
      "missing": [
        "facebook_pixel",
        "google_ads_remarketing",
        "google_tag_manager",
        "tiktok_pixel",
        "linkedin_insight"
      ],
      "found": [
        "google_analytics"
      ],
      "google_ads_conversion": false,
      "pages_scanned": [
        "https://www.portebrown.com/office-locations/elgin",
        "https://www.portebrown.com/contact-us",
        "https://www.portebrown.com/services"
      ],
      "source": "playwright_v2"
    },
    "fetch_status": "ok",
    "_source": "google_maps_pixel_audit",
    "opportunity_score": 8.5,
    "pixels_v2": {
      "status": "ok",
      "error": null,
      "facebook_pixel": false,
      "google_ads_remarketing": false,
      "google_ads_conversion": false,
      "google_analytics": true,
      "google_tag_manager": false,
      "linkedin_insight": false,
      "tiktok_pixel": false,
      "any_retargeting": false,
      "pages_scanned": [
        "https://www.portebrown.com/office-locations/elgin",
        "https://www.portebrown.com/contact-us",
        "https://www.portebrown.com/services"
      ],
      "errors": [],
      "source": "playwright_v2"
    },
    "pixel_audit_status": "ok"
  },
  {
    "business_name": "Ritsons Chartered Accountants Limited",
    "business_category": "accountant",
    "city": "elgin",
    "address": "103 High St, Elgin IV30, UK",
    "phone_number": "",
    "website_url": "http://www.ritsonsca.com/",
    "google_maps_url": "https://maps.google.com/?cid=12083108427600909555&g_mp=Cidnb29nbGUubWFwcy5wbGFjZXMudjEuUGxhY2VzLlNlYXJjaFRleHQQAhgEIAA",
    "rating": 5,
    "review_count": 1,
    "pixel_audit": {
      "tracking_score": 15,
      "any_retargeting": false,
      "facebook_pixel": false,
      "facebook_pixel_id": "",
      "google_ads_remarketing": false,
      "google_ads_id": "",
      "google_analytics": true,
      "google_tag_manager": false,
      "tiktok_pixel": false,
      "linkedin_insight": false,
      "hotjar": false,
      "any_tag_manager": false,
      "missing": [
        "facebook_pixel",
        "google_ads_remarketing",
        "google_tag_manager",
        "tiktok_pixel",
        "linkedin_insight"
      ],
      "found": [
        "google_analytics"
      ],
      "google_ads_conversion": false,
      "pages_scanned": [
        "http://www.ritsonsca.com/"
      ],
      "source": "playwright_v2"
    },
    "fetch_status": "ok",
    "_source": "google_maps_pixel_audit",
    "opportunity_score": 4.2,
    "pixels_v2": {
      "status": "ok",
      "error": null,
      "facebook_pixel": false,
      "google_ads_remarketing": false,
      "google_ads_conversion": false,
      "google_analytics": true,
      "google_tag_manager": false,
      "linkedin_insight": false,
      "tiktok_pixel": false,
      "any_retargeting": false,
      "pages_scanned": [
        "http://www.ritsonsca.com/"
      ],
      "errors": [],
      "source": "playwright_v2"
    },
    "pixel_audit_status": "ok"
  },
  {
    "business_name": "Goldwells",
    "business_category": "accountant",
    "city": "elgin",
    "address": "Wards House, Wards Rd, Elgin IV30 1NL, UK",
    "phone_number": "01343 551671",
    "website_url": "http://goldwells.com/",
    "google_maps_url": "https://maps.google.com/?cid=12168174872162441399&g_mp=Cidnb29nbGUubWFwcy5wbGFjZXMudjEuUGxhY2VzLlNlYXJjaFRleHQQAhgEIAA",
    "rating": 5,
    "review_count": 1,
    "pixel_audit": {
      "tracking_score": 15,
      "any_retargeting": false,
      "facebook_pixel": false,
      "facebook_pixel_id": "",
      "google_ads_remarketing": false,
      "google_ads_id": "",
      "google_analytics": true,
      "google_tag_manager": false,
      "tiktok_pixel": false,
      "linkedin_insight": false,
      "hotjar": false,
      "any_tag_manager": false,
      "missing": [
        "facebook_pixel",
        "google_ads_remarketing",
        "google_tag_manager",
        "tiktok_pixel",
        "linkedin_insight"
      ],
      "found": [
        "google_analytics"
      ],
      "google_ads_conversion": false,
      "pages_scanned": [
        "http://goldwells.com/"
      ],
      "source": "playwright_v2"
    },
    "fetch_status": "ok",
    "_source": "google_maps_pixel_audit",
    "opportunity_score": 4.2,
    "pixels_v2": {
      "status": "ok",
      "error": null,
      "facebook_pixel": false,
      "google_ads_remarketing": false,
      "google_ads_conversion": false,
      "google_analytics": true,
      "google_tag_manager": false,
      "linkedin_insight": false,
      "tiktok_pixel": false,
      "any_retargeting": false,
      "pages_scanned": [
        "http://goldwells.com/"
      ],
      "errors": [],
      "source": "playwright_v2"
    },
    "pixel_audit_status": "ok"
  },
  {
    "business_name": "PK Tax Services, L.L.C.",
    "business_category": "accountant",
    "city": "elgin",
    "address": "87 S McLean Blvd, South Elgin, IL 60177, USA",
    "phone_number": "(224) 227-6061",
    "website_url": "http://www.pktaxservices.com/",
    "google_maps_url": "https://maps.google.com/?cid=12571911242913848339&g_mp=Cidnb29nbGUubWFwcy5wbGFjZXMudjEuUGxhY2VzLlNlYXJjaFRleHQQAhgEIAA",
    "rating": 4.1,
    "review_count": 16,
    "pixel_audit": {
      "tracking_score": 65,
      "any_retargeting": true,
      "facebook_pixel": true,
      "facebook_pixel_id": "386692628604820",
      "google_ads_remarketing": true,
      "google_ads_id": "AW-803261655",
      "google_analytics": true,
      "google_tag_manager": false,
      "tiktok_pixel": false,
      "linkedin_insight": false,
      "hotjar": false,
      "any_tag_manager": false,
      "missing": [
        "google_tag_manager",
        "tiktok_pixel",
        "linkedin_insight"
      ],
      "found": [
        "facebook_pixel",
        "google_ads_remarketing",
        "google_analytics"
      ],
      "google_ads_conversion": false,
      "pages_scanned": [
        "http://www.pktaxservices.com/"
      ],
      "source": "playwright_v2"
    },
    "fetch_status": "ok",
    "_source": "google_maps_pixel_audit",
    "opportunity_score": 23.0,
    "pixels_v2": {
      "status": "ok",
      "error": null,
      "facebook_pixel": true,
      "google_ads_remarketing": true,
      "google_ads_conversion": false,
      "google_analytics": true,
      "google_tag_manager": false,
      "linkedin_insight": false,
      "tiktok_pixel": false,
      "any_retargeting": true,
      "pages_scanned": [
        "http://www.pktaxservices.com/"
      ],
      "errors": [],
      "source": "playwright_v2"
    },
    "pixel_audit_status": "ok"
  },
  {
    "business_name": "Johnston Carmichael Chartered Accountants & Business Advisers Elgin",
    "business_category": "accountant",
    "city": "elgin",
    "address": "Strathlossie House, 1 Kirkhill Ave, Elgin IV30 8DE, UK",
    "phone_number": "01343 547492",
    "website_url": "https://johnstoncarmichael.com/locations/chartered-accountants-elgin?utm_source=gmb&utm_medium=organic&utm_campaign=elgin",
    "google_maps_url": "https://maps.google.com/?cid=15340835484738615549&g_mp=Cidnb29nbGUubWFwcy5wbGFjZXMudjEuUGxhY2VzLlNlYXJjaFRleHQQAhgEIAA",
    "rating": 0,
    "review_count": 0,
    "pixel_audit": {
      "tracking_score": 15,
      "any_retargeting": true,
      "facebook_pixel": true,
      "facebook_pixel_id": "",
      "google_ads_remarketing": true,
      "google_ads_id": "",
      "google_analytics": true,
      "google_tag_manager": true,
      "tiktok_pixel": false,
      "linkedin_insight": true,
      "hotjar": false,
      "any_tag_manager": true,
      "missing": [
        "facebook_pixel",
        "google_ads_remarketing",
        "google_analytics",
        "tiktok_pixel",
        "linkedin_insight"
      ],
      "found": [
        "google_tag_manager"
      ],
      "google_ads_conversion": false,
      "pages_scanned": [
        "https://johnstoncarmichael.com/locations/chartered-accountants-elgin?utm_source=gmb&utm_medium=organic&utm_campaign=elgin",
        "https://johnstoncarmichael.com/contact/"
      ],
      "source": "playwright_v2"
    },
    "fetch_status": "ok",
    "_source": "google_maps_pixel_audit",
    "opportunity_score": 0.0,
    "pixels_v2": {
      "status": "ok",
      "error": null,
      "facebook_pixel": true,
      "google_ads_remarketing": true,
      "google_ads_conversion": false,
      "google_analytics": true,
      "google_tag_manager": true,
      "linkedin_insight": true,
      "tiktok_pixel": false,
      "any_retargeting": true,
      "pages_scanned": [
        "https://johnstoncarmichael.com/locations/chartered-accountants-elgin?utm_source=gmb&utm_medium=organic&utm_campaign=elgin",
        "https://johnstoncarmichael.com/contact/"
      ],
      "errors": [],
      "source": "playwright_v2"
    },
    "pixel_audit_status": "ok"
  }
]