[
  {
    "business_name": "The Glasgow Law Practice",
    "business_category": "solicitor",
    "city": "cambuslang",
    "address": "124 Main St, Cambuslang, Glasgow G72 7EL, UK",
    "phone_number": "0141 641 2912",
    "website_url": "https://www.theglasgowlawpractice.co.uk/",
    "google_maps_url": "https://maps.google.com/?cid=5333257734226106161&g_mp=Cidnb29nbGUubWFwcy5wbGFjZXMudjEuUGxhY2VzLlNlYXJjaFRleHQQAhgEIAA",
    "rating": 4.1,
    "review_count": 30,
    "pixel_audit": {
      "tracking_score": 40,
      "any_retargeting": false,
      "facebook_pixel": false,
      "facebook_pixel_id": "",
      "google_ads_remarketing": false,
      "google_ads_id": "",
      "google_analytics": true,
      "google_tag_manager": true,
      "tiktok_pixel": false,
      "linkedin_insight": false,
      "hotjar": false,
      "any_tag_manager": true,
      "missing": [
        "facebook_pixel",
        "google_analytics",
        "tiktok_pixel",
        "linkedin_insight"
      ],
      "found": [
        "google_ads_remarketing",
        "google_tag_manager"
      ],
      "google_ads_conversion": false,
      "pages_scanned": [
        "https://www.theglasgowlawpractice.co.uk/",
        "https://www.theglasgowlawpractice.co.uk/contact-us/"
      ],
      "source": "playwright_v2"
    },
    "fetch_status": "ok",
    "_source": "google_maps_pixel_audit",
    "opportunity_score": 73.8,
    "pixels_v2": {
      "status": "ok",
      "error": null,
      "facebook_pixel": false,
      "google_ads_remarketing": false,
      "google_ads_conversion": false,
      "google_analytics": true,
      "google_tag_manager": true,
      "linkedin_insight": false,
      "tiktok_pixel": false,
      "any_retargeting": false,
      "pages_scanned": [
        "https://www.theglasgowlawpractice.co.uk/",
        "https://www.theglasgowlawpractice.co.uk/contact-us/"
      ],
      "errors": [],
      "source": "playwright_v2"
    },
    "pixel_audit_status": "ok"
  }
]